odoo/addons/geoengine_bing/README.rst
odoo/addons/geoengine_bing/__init__.py
odoo/addons/geoengine_bing/__manifest__.py
odoo/addons/geoengine_bing/geo_view/__init__.py
odoo/addons/geoengine_bing/geo_view/geo_raster_layer.py
odoo/addons/geoengine_bing/geo_view/geo_raster_layer_view.xml
odoo/addons/geoengine_bing/i18n/geoengine_bing.pot
odoo/addons/geoengine_bing/static/description/icon.png
odoo/addons/geoengine_bing/static/src/js/geoengine_common.js
odoo/addons/geoengine_bing/views/geoengine_bing_view.xml
odoo12_addon_geoengine_bing-12.0.1.0.2.dist-info/METADATA
odoo12_addon_geoengine_bing-12.0.1.0.2.dist-info/WHEEL
odoo12_addon_geoengine_bing-12.0.1.0.2.dist-info/top_level.txt
odoo12_addon_geoengine_bing-12.0.1.0.2.dist-info/RECORD
